runner/__init__.py
runner/__main__.py
runner/factory.py
runner/load.py
runner/plot.py
runner/run.py
runner/action/__init__.py
runner/action/action.py
runner/action/feature/__init__.py
runner/action/feature/feature.py
runner/action/feature/feature_categorical.py
runner/action/feature/feature_categorical_file.py
runner/action/feature/feature_categorical_foam.py
runner/action/feature/feature_categorical_json.py
runner/action/feature/feature_categorical_yaml.py
runner/action/feature/feature_continuous.py
runner/action/feature/feature_continuous_file.py
runner/action/feature/feature_continuous_foam.py
runner/action/feature/feature_continuous_json.py
runner/action/feature/feature_continuous_yaml.py
runner/action/feature/feature_discrete.py
runner/action/feature/feature_discrete_file.py
runner/action/feature/feature_discrete_foam.py
runner/action/feature/feature_discrete_json.py
runner/action/feature/feature_discrete_yaml.py
runner/action/feature/feature_equation.py
runner/action/feature/feature_regex.py
runner/action/get/__init__.py
runner/action/get/get.py
runner/action/get/file/__init__.py
runner/action/get/file/file.py
runner/action/get/file/template.py
runner/action/get/file/markup/__init__.py
runner/action/get/file/markup/foam.py
runner/action/get/file/markup/json.py
runner/action/get/file/markup/markup.py
runner/action/get/file/markup/yaml.py
runner/action/optimize/__init__.py
runner/action/optimize/optimize.py
runner/action/optimize/optuna.py
runner/action/run/__init__.py
runner/action/run/run.py
runner/action/run/subprocess.py
runner/action/set/__init__.py
runner/action/set/categorical.py
runner/action/set/continuous.py
runner/action/set/discrete.py
runner/action/set/equation.py
runner/action/set/set.py
runner/action/set/value.py
runner/action/set/variable.py
runner/action/set/file/__init__.py
runner/action/set/file/file.py
runner/action/set/file/regex.py
runner/tests/__init__.py
runner/tests/conftest.py
runner/tests/action/__init__.py
mltrip_runner-0.1.7.dist-info/LICENSE
mltrip_runner-0.1.7.dist-info/METADATA
mltrip_runner-0.1.7.dist-info/WHEEL
mltrip_runner-0.1.7.dist-info/top_level.txt
mltrip_runner-0.1.7.dist-info/RECORD
